binary_to_bcd_big.v
`timescale 10ns/1ns

module binary_to_bcd_big(
	input clk,
	input [15:0] sixteen_bit_value,
	output reg [3:0] ones = 0,
	output reg [3:0] tens = 0,
	output reg [3:0] hundreds = 0,
	output reg [3:0] thousands = 0
	);
	
reg [3:0] i = 0;
reg [23:0] shift_register = 0;
reg [3:0] temp_ones = 0;
reg [3:0] temp_tens = 0;
reg [3:0] temp_hunndreds = 0;
reg [3:0] temp_thousands = 0;
reg [15:0] old_sixteen_bit_value = 0;

always @(posedge clk)
	begin
		if((i==0) & (old_sixteen_bit_value != sixteen_bit_value))
			begin
				shift_register = 24'd0;
				old_sixteen_bit_value = sixteen_bit_value;
				shift_register[15:0] = sixteen_bit_value;
				temp_thousands = shift_register[23:20];
				temp_hunndreds = shift_register[19:16];
				temp_tens = shift_register[15:12];
				temp_ones = shift_register[11:8];
				i = i + 1;
			end
		if(i < 9 & i > 0)
			begin
				if(temp_thousands >= 5) temp_thousands = temp_thousands + 3;
				if(temp_hunndreds >= 5) temp_hunndreds = temp_hunndreds + 3;
				if(temp_tens >= 5) temp_tens = temp_tens + 3;
				if(temp_ones >= 5) temp_ones = temp_ones + 3;
				shift_register[19:8] = {temp_thousands, temp_hunndreds, temp_tens, temp_ones};
				shift_register	= shift_register << 1;
				temp_thousands = shift_register[23:20];
				temp_hunndreds = shift_register[19:16];
				temp_tens = shift_register[15:12];
				temp_ones = shift_register[11:8];
				i = i + 1;
			end
		if(i == 9)
			begin
				i = 0;
				thousands = temp_thousands;
				hundreds = temp_hunndreds;
				tens = temp_tens;
				ones = temp_ones;
			end
	end
endmodule

binary_to_bcd_big_test.v
`timescale 10ns/1ns

module binary_to_bcd_big_test;
	reg clk = 0;
	reg [15:0] sixteen_bit_value = 0;
	wire [3:0] ones;
	wire [3:0] tens;
	wire [3:0] hundreds;
	wire [3:0] thousands;
	
binary_to_bcd_big DUT(.clk(clk), .sixteen_bit_value(sixteen_bit_value), .ones(ones), .tens(tens), .hundreds(hundreds), .thousands(thousands));

always
	#5 clk = ~clk;
	
initial
	begin
		$dumpfile("binary_to_bcd_big_test.vcd");
		$dumpvars(0, binary_to_bcd_big_test);
		$monitor($time, "clk = %b, eight_bit_value = %d, thousands = %b, hundreds = %b, tens = %b, ones = %b", clk, sixteen_bit_value, thousands, hundreds, tens, ones);
		sixteen_bit_value = 0;
		#500 sixteen_bit_value = 10;
		#500 sixteen_bit_value = 589;
		#500 sixteen_bit_value = 2375;
		#1000 $finish;
	end
endmodule

binary_to_bcd_big_test.vcd
$date
	Tue Apr 14 21:10:42 2020
$end
$version
	Icarus Verilog
$end
$timescale
	1ns
$end
$scope module binary_to_bcd_big_test $end
$var wire 4 ! thousands [3:0] $end
$var wire 4 " tens [3:0] $end
$var wire 4 # ones [3:0] $end
$var wire 4 $ hundreds [3:0] $end
$var reg 1 % clk $end
$var reg 16 & sixteen_bit_value [15:0] $end
$scope module DUT $end
$var wire 1 % clk $end
$var wire 16 ' sixteen_bit_value [15:0] $end
$var reg 4 ( hundreds [3:0] $end
$var reg 4 ) i [3:0] $end
$var reg 16 * old_sixteen_bit_value [15:0] $end
$var reg 4 + ones [3:0] $end
$var reg 24 , shift_register [23:0] $end
$var reg 4 - temp_hunndreds [3:0] $end
$var reg 4 . temp_ones [3:0] $end
$var reg 4 / temp_tens [3:0] $end
$var reg 4 0 temp_thousands [3:0] $end
$var reg 4 1 tens [3:0] $end
$var reg 4 2 thousands [3:0] $end
$upscope $end
$upscope $end
$enddefinitions $end
#0
$dumpvars
b0 2
b0 1
b0 0
b0 /
b0 .
b0 -
b0 ,
b0 +
b0 *
b0 )
b0 (
b0 '
b0 &
0%
b0 $
b0 #
b0 "
b0 !
$end
#50
1%
#100
0%
#150
1%
#200
0%
#250
1%
#300
0%
#350
1%
#400
0%
#450
1%
#500
0%
#550
1%
#600
0%
#650
1%
#700
0%
#750
1%
#800
0%
#850
1%
#900
0%
#950
1%
#1000
0%
#1050
1%
#1100
0%
#1150
1%
#1200
0%
#1250
1%
#1300
0%
#1350
1%
#1400
0%
#1450
1%
#1500
0%
#1550
1%
#1600
0%
#1650
1%
#1700
0%
#1750
1%
#1800
0%
#1850
1%
#1900
0%
#1950
1%
#2000
0%
#2050
1%
#2100
0%
#2150
1%
#2200
0%
#2250
1%
#2300
0%
#2350
1%
#2400
0%
#2450
1%
#2500
0%
#2550
1%
#2600
0%
#2650
1%
#2700
0%
#2750
1%
#2800
0%
#2850
1%
#2900
0%
#2950
1%
#3000
0%
#3050
1%
#3100
0%
#3150
1%
#3200
0%
#3250
1%
#3300
0%
#3350
1%
#3400
0%
#3450
1%
#3500
0%
#3550
1%
#3600
0%
#3650
1%
#3700
0%
#3750
1%
#3800
0%
#3850
1%
#3900
0%
#3950
1%
#4000
0%
#4050
1%
#4100
0%
#4150
1%
#4200
0%
#4250
1%
#4300
0%
#4350
1%
#4400
0%
#4450
1%
#4500
0%
#4550
1%
#4600
0%
#4650
1%
#4700
0%
#4750
1%
#4800
0%
#4850
1%
#4900
0%
#4950
1%
#5000
0%
b1010 &
b1010 '
#5050
b10 )
b10100 ,
b1010 *
1%
#5100
0%
#5150
b11 )
b101000 ,
1%
#5200
0%
#5250
b100 )
b1010000 ,
1%
#5300
0%
#5350
b101 )
b10100000 ,
1%
#5400
0%
#5450
b110 )
b1 .
b101000000 ,
1%
#5500
0%
#5550
b111 )
b10 .
b1010000000 ,
1%
#5600
0%
#5650
b1000 )
b101 .
b10100000000 ,
1%
#5700
0%
#5750
b1 "
b1 1
b0 )
b1 /
b1000000000000 ,
b0 .
1%
